ethsential/__init__.py
ethsential/__main__.py
ethsential/__version__.py
ethsential/src/__init__.py
ethsential/src/parser.py
ethsential/src/parser_test.py
ethsential/src/services.py
ethsential/src/applications/__init__.py
ethsential/src/applications/cli.py
ethsential/src/applications/server.py
ethsential/src/tools/__init__.py
ethsential/src/tools/mythril.py
ethsential/src/tools/result.py
ethsential/src/tools/securify.py
ethsential/src/tools/slither.py
ethsential/src/tools/tool.py
ethsential/src/tools/tool_factory.py
ethsential/src/tools/tool_factory_test.py
ethsential-0.2.6.dist-info/LICENSE
ethsential-0.2.6.dist-info/METADATA
ethsential-0.2.6.dist-info/WHEEL
ethsential-0.2.6.dist-info/entry_points.txt
ethsential-0.2.6.dist-info/top_level.txt
ethsential-0.2.6.dist-info/RECORD
