Metadata-Version: 2.1
Name: ethsential
Version: 0.2.6
Summary: EthSential package for Python-Guide.org
Home-page: https://github.com/1140251/Ethsential
Author: Daniel Dias
License: Apache-2.0
Platform: UNKNOWN
Requires-Dist: docker (==4.2.1)
Requires-Dist: pygls (==0.9.0)
Requires-Dist: joblib (==0.16.0)
Requires-Dist: solidity-parser (==0.0.7)
